gavincheng_weather/__main__.py
gavincheng_weather/weather.py
gavincheng_weather-0.1.5.dist-info/METADATA
gavincheng_weather-0.1.5.dist-info/WHEEL
gavincheng_weather-0.1.5.dist-info/entry_points.txt
gavincheng_weather-0.1.5.dist-info/top_level.txt
gavincheng_weather-0.1.5.dist-info/RECORD
