Metadata-Version: 2.4
Name: gavincheng-weather
Version: 0.1.5
Summary: Add your description here
Requires-Python: >=3.13
Requires-Dist: httpx>=0.28.1
Requires-Dist: mcp[cli]>=1.6.0
